<annotation>
	<folder>n07720875</folder>
	<filename>n07720875_5010.jpg</filename>
	<source>
		<database>ImageNet database</database>
	</source>
	<size>
		<width>500</width>
		<height>375</height>
		<depth>3</depth>
	</size>
	<segmented>0</segmented>
	<object>
		<name>capsicum</name>
		<pose>Unspecified</pose>
		<truncated>0</truncated>
		<difficult>0</difficult>
		<bndbox>
			<xmin>37</xmin>
			<ymin>68</ymin>
			<xmax>212</xmax>
			<ymax>256</ymax>
		</bndbox>
	</object>
	<object>
		<name>capsicum</name>
		<pose>Unspecified</pose>
		<truncated>0</truncated>
		<difficult>0</difficult>
		<bndbox>
			<xmin>212</xmin>
			<ymin>101</ymin>
			<xmax>413</xmax>
			<ymax>280</ymax>
		</bndbox>
	</object>
	<object>
		<name>capsicum</name>
		<pose>Unspecified</pose>
		<truncated>0</truncated>
		<difficult>0</difficult>
		<bndbox>
			<xmin>129</xmin>
			<ymin>12</ymin>
			<xmax>296</xmax>
			<ymax>164</ymax>
		</bndbox>
	</object>
</annotation>