<annotation>
	<folder>n07754684</folder>
	<filename>n07754684_7103.jpg</filename>
	<source>
		<database>ImageNet database</database>
	</source>
	<size>
		<width>432</width>
		<height>323</height>
		<depth>3</depth>
	</size>
	<segmented>0</segmented>
	<object>
		<name>jackfruit</name>
		<pose>Unspecified</pose>
		<truncated>0</truncated>
		<difficult>0</difficult>
		<bndbox>
			<xmin>167</xmin>
			<ymin>80</ymin>
			<xmax>254</xmax>
			<ymax>224</ymax>
		</bndbox>
	</object>
	<object>
		<name>jackfruit</name>
		<pose>Unspecified</pose>
		<truncated>0</truncated>
		<difficult>0</difficult>
		<bndbox>
			<xmin>148</xmin>
			<ymin>186</ymin>
			<xmax>191</xmax>
			<ymax>245</ymax>
		</bndbox>
	</object>
</annotation>