<annotation>
	<folder>n07754684</folder>
	<filename>n07754684_5419.jpg</filename>
	<source>
		<database>ImageNet database</database>
	</source>
	<size>
		<width>182</width>
		<height>130</height>
		<depth>3</depth>
	</size>
	<segmented>0</segmented>
	<object>
		<name>jackfruit</name>
		<pose>Unspecified</pose>
		<truncated>0</truncated>
		<difficult>0</difficult>
		<bndbox>
			<xmin>67</xmin>
			<ymin>15</ymin>
			<xmax>99</xmax>
			<ymax>45</ymax>
		</bndbox>
	</object>
	<object>
		<name>jackfruit</name>
		<pose>Unspecified</pose>
		<truncated>0</truncated>
		<difficult>0</difficult>
		<bndbox>
			<xmin>3</xmin>
			<ymin>3</ymin>
			<xmax>163</xmax>
			<ymax>129</ymax>
		</bndbox>
	</object>
</annotation>